destnosim/.DS_Store
destnosim/__init__.py
destnosim/des/__init__.py
destnosim/des/ccd.py
destnosim/des/decam.py
destnosim/des/deep.py
destnosim/des/des.py
destnosim/des/testccd.py
destnosim/tno/__init__.py
destnosim/tno/distribution.py
destnosim/tno/inv_sample.py
destnosim/tno/magnitude.py
destnosim/tno/popstat.py
destnosim/tno/population.py
destnosim/tno/transformation.py
DESTNOSIM-1.2.2.dist-info/METADATA
DESTNOSIM-1.2.2.dist-info/WHEEL
DESTNOSIM-1.2.2.dist-info/top_level.txt
DESTNOSIM-1.2.2.dist-info/RECORD
