Metadata-Version: 2.1
Name: DESTNOSIM
Version: 1.2.2
Summary: Python module for simulating DES TNO observations
Home-page: https://github.com/bernardinelli/DESTNOSIM
Author: Pedro Bernardinelli
Author-email: pedrobe@sas.upenn.edu
License: BSD License
Platform: UNKNOWN
Requires-Dist: numpy
Requires-Dist: astropy
Requires-Dist: scipy
Requires-Dist: numba
Requires-Dist: spacerocks
